OpenMedicalChatBox/__init__.py
OpenMedicalChatBox/version.py
OpenMedicalChatBox/Flat_DQN/BLEU.py
OpenMedicalChatBox/Flat_DQN/__init__.py
OpenMedicalChatBox/Flat_DQN/bound.py
OpenMedicalChatBox/Flat_DQN/dialogue_configuration.py
OpenMedicalChatBox/Flat_DQN/disease_classifier.py
OpenMedicalChatBox/Flat_DQN/run.py
OpenMedicalChatBox/Flat_DQN/run_for_parameter.py
OpenMedicalChatBox/Flat_DQN/running_steward.py
OpenMedicalChatBox/Flat_DQN/utils.py
OpenMedicalChatBox/Flat_DQN/agent/__init__.py
OpenMedicalChatBox/Flat_DQN/agent/agent.py
OpenMedicalChatBox/Flat_DQN/agent/agent_dqn.py
OpenMedicalChatBox/Flat_DQN/agent/agent_dqn_new.py
OpenMedicalChatBox/Flat_DQN/agent/agent_random.py
OpenMedicalChatBox/Flat_DQN/agent/agent_rule.py
OpenMedicalChatBox/Flat_DQN/agent/dialogue_configuration.py
OpenMedicalChatBox/Flat_DQN/agent/utils.py
OpenMedicalChatBox/Flat_DQN/dialogue_manager/__init__.py
OpenMedicalChatBox/Flat_DQN/dialogue_manager/dialogue_manager.py
OpenMedicalChatBox/Flat_DQN/policy_learning/__init__.py
OpenMedicalChatBox/Flat_DQN/policy_learning/dqn.py
OpenMedicalChatBox/Flat_DQN/policy_learning/dqn_goal.py
OpenMedicalChatBox/Flat_DQN/policy_learning/dqn_torch.py
OpenMedicalChatBox/Flat_DQN/policy_learning/dqn_torch_new.py
OpenMedicalChatBox/Flat_DQN/state_tracker/__init__.py
OpenMedicalChatBox/Flat_DQN/state_tracker/state_tracker.py
OpenMedicalChatBox/Flat_DQN/user_simulator/__init__.py
OpenMedicalChatBox/Flat_DQN/user_simulator/user.py
OpenMedicalChatBox/Flat_DQN/user_simulator/user_rule.py
OpenMedicalChatBox/GAMP/__init__.py
OpenMedicalChatBox/GAMP/agent.py
OpenMedicalChatBox/GAMP/dataloader.py
OpenMedicalChatBox/GAMP/network.py
OpenMedicalChatBox/GAMP/run.py
OpenMedicalChatBox/GAMP/running_steward.py
OpenMedicalChatBox/GAMP/toy_model.py
OpenMedicalChatBox/GAMP/utils.py
OpenMedicalChatBox/HRL/BLEU.py
OpenMedicalChatBox/HRL/__init__.py
OpenMedicalChatBox/HRL/bound.py
OpenMedicalChatBox/HRL/dialogue_configuration.py
OpenMedicalChatBox/HRL/disease_classifier.py
OpenMedicalChatBox-1.1.0.dist-info/METADATA
OpenMedicalChatBox-1.1.0.dist-info/WHEEL
OpenMedicalChatBox-1.1.0.dist-info/top_level.txt
OpenMedicalChatBox-1.1.0.dist-info/RECORD
