Metadata-Version: 2.1
Name: OpenMedicalChatBox
Version: 1.1.0
Summary: OpenMedicalChatBox
Home-page: https://github.com/Guardianzc/OpenMedicalChatBox
Author: Cheng Zhong
Author-email: zhong7414@gmail.com
License: UNKNOWN
Platform: UNKNOWN
Classifier: Programming Language :: Python :: 3
Classifier: License :: OSI Approved :: MIT License
Classifier: Operating System :: OS Independent
Requires-Python: >=3.8
Requires-Dist: numpy
Requires-Dist: torch
Requires-Dist: tensorflow
Requires-Dist: tensorflow-gpu
Requires-Dist: google
Requires-Dist: pandas
Requires-Dist: argparse
Requires-Dist: logging
Requires-Dist: datetime
